{
    "african blues": "blues",
    "blues rock": "blues",
    "blues shouter": "blues",
    "british blues": "blues",
    "canadian blues": "blues",
    "chicago blues": "blues",
    "classic female blues": "blues",
    "contemporary r&amp;b": "r&b/soul",
    "country blues": "country",
    "delta blues": "blues",
    "detroit blues": "blues",
    "electric blues": "blues",
    "funk blues": "blues",
    "gospel blues": "blues",
    "hill country blues": "blues",
    "hokum": "country",
    "jump blues": "blues",
    "kansas city blues": "jazz",
    "louisiana blues": "blues",
    "memphis blues": "blues",
    "piedmont blues": "blues",
    "punk blues": "blues",
    "rhythm and blues": "r&b/soul",
    "soul blues": "blues",
    "st. louis blues": "blues",
    "swamp blues": "blues",
    "texas blues": "blues",
    "west coast blues": "blues",
    "ambient music": "electronic",
    "ambient dub": "electronic",
    "dark ambient": "electronic",
    "drone music": "electronic",
    "space music": "electronic",
    "illbient": "electronic",
    "psybient": "electronic",
    "isolationism": "electronic",
    "asian underground": "electronic",
    "breakbeat": "electronic",
    "acid breaks": "electronic",
    "baltimore club": "electronic",
    "big beat": "electronic",
    "broken beat": "electronic",
    "florida breaks": "electronic",
    "nu-funk": "electronic",
    "miami bass": "electronic",
    "jersey club": "hip-hop/rap",
    "nu skool breaks": "electronic",
    "disco": "r&b/soul",
    "afro/cosmic music": "electronic",
    "disco polo": "pop",
    "euro disco": "electronic",
    "italo disco": "pop",
    "nu-disco": "electronic",
    "space disco": "electronic",
    "downtempo": "electronic",
    "acid jazz": "jazz",
    "chill-out music": "electronic",
    "new-age music": "classical",
    "trip hop": "electronic",
    "drum and bass": "electronic",
    "liquid funk": "electronic",
    "neurofunk": "electronic",
    "neurohop": "electronic",
    "jump-up": "electronic",
    "darkstep": "electronic",
    "drumstep": "electronic",
    "funkstep": "electronic",
    "hardstep": "electronic",
    "sambass": "electronic",
    "techstep": "electronic",
    "dub music": "electronic",
    "dancehall": "electronic",
    "dub poetry": "electronic",
    "dub reggae": "electronic",
    "dub techno": "electronic",
    "dubstep": "electronic",
    "dubtronica": "electronic",
    "electro music": "hip-hop/rap",
    "freestyle music": "r&b/soul",
    "electroacoustic music": "electronic",
    "acousmatic music": "electronic",
    "musique concr\u00e8te": "electronic",
    "electronic dance music": "electronic",
    "electronic rock": "rock",
    "alternative dance": "electronic",
    "indietronica": "electronic",
    "coldwave": "electronic",
    "dance-punk": "electronic",
    "dark wave": "electronic",
    "electroclash": "electronic",
    "electronicore": "rock",
    "electropunk": "electronic",
    "ethereal wave": "electronic",
    "krautrock": "rock",
    "minimal wave": "electronic",
    "new rave": "electronic",
    "nu-gaze": "electronic",
    "space rock": "rock",
    "synthpop": "pop",
    "electronica": "electronic",
    "berlin school of electronic music": "electronic",
    "ethnic electronica": "electronic",
    "folktronica": "country",
    "funktronica": "electronic",
    "laptronica": "electronic",
    "livetronica": "jazz",
    "hardcore": "electronic",
    "gabber": "electronic",
    "4-beat": "electronic",
    "breakbeat hardcore": "electronic",
    "bouncy techno": "electronic",
    "breakcore": "electronic",
    "digital hardcore": "rock",
    "darkcore": "electronic",
    "happy hardcore": "electronic",
    "m\u00e1kina": "electronic",
    "speedcore": "electronic",
    "uk hardcore": "electronic",
    "doomcore": "electronic",
    "hardstyle": "electronic",
    "dubstyle": "electronic",
    "jumpstyle": "electronic",
    "lento violento": "electronic",
    "hardbass": "electronic",
    "hi-nrg": "electronic",
    "eurobeat": "pop",
    "eurodance": "electronic",
    "bubblegum dance": "electronic",
    "italo dance": "pop",
    "house music": "electronic",
    "acid house": "electronic",
    "ambient house": "electronic",
    "balearic beat": "electronic",
    "chicago house": "electronic",
    "deep house": "electronic",
    "future house": "electronic",
    "tropical house": "electronic",
    "diva house": "electronic",
    "electro house": "electronic",
    "big room house": "electronic",
    "complextro": "electronic",
    "fidget house": "electronic",
    "dutch house": "electronic",
    "moombahton": "electronic",
    "moombahcore": "electronic",
    "french house": "electronic",
    "funky house": "electronic",
    "garage house": "electronic",
    "ghetto house": "hip-hop/rap",
    "ghettotech": "hip-hop/rap",
    "hardbag": "electronic",
    "hard house": "electronic",
    "hard dance": "electronic",
    "hard nrg": "electronic",
    "hip house": "hip-hop/rap",
    "italo house": "electronic",
    "nu jazz": "jazz",
    "kidandali": "electronic",
    "kwaito": "hip-hop/rap",
    "latin house": "electronic",
    "microhouse": "electronic",
    "new beat": "electronic",
    "outsider house": "electronic",
    "progressive house": "electronic",
    "rara tech": "electronic",
    "tech house": "electronic",
    "tribal house": "electronic",
    "trival": "electronic",
    "witch house": "electronic",
    "industrial music": "electronic",
    "aggrotech": "electronic",
    "electrogrind": "electronic",
    "electro-industrial": "electronic",
    "dark electro": "electronic",
    "electronic body music": "electronic",
    "futurepop": "electronic",
    "industrial metal": "rock",
    "industrial rock": "rock",
    "japanoise": "electronic",
    "martial industrial": "electronic",
    "neue deutsche h\u00e4rte": "rock",
    "power electronics": "electronic",
    "death industrial": "electronic",
    "power noise": "electronic",
    "intelligent dance music": "electronic",
    "glitch music": "electronic",
    "glitch hop": "electronic",
    "wonky": "electronic",
    "oldschool jungle": "electronic",
    "raggacore": "electronic",
    "post-disco": "r&b/soul",
    "boogie": "r&b/soul",
    "electropop": "pop",
    "chillwave": "electronic",
    "vaporwave": "electronic",
    "dance-pop": "pop",
    "dance-rock": "electronic",
    "techno": "electronic",
    "acid techno": "electronic",
    "detroit techno": "electronic",
    "free tekno": "electronic",
    "minimal techno": "electronic",
    "nortec": "electronic",
    "tecno brega": "electronic",
    "techdombe": "electronic",
    "trance music": "electronic",
    "acid trance": "electronic",
    "balearic trance": "electronic",
    "dream trance": "electronic",
    "euro-trance": "electronic",
    "hard trance": "electronic",
    "nitzhonot": "electronic",
    "psychedelic trance": "electronic",
    "full on": "electronic",
    "suomisaundi": "electronic",
    "goa trance": "electronic",
    "progressive trance": "electronic",
    "tech trance": "electronic",
    "uplifting trance": "electronic",
    "vocal trance": "electronic",
    "uk garage": "electronic",
    "2-step garage": "electronic",
    "brostep": "electronic",
    "chillstep": "electronic",
    "reggaestep": "electronic",
    "trapstep": "electronic",
    "metalstep": "rock",
    "vomitstep": "electronic",
    "breakstep": "electronic",
    "future garage": "electronic",
    "grime music": "electronic",
    "grindie": "electronic",
    "speed garage": "electronic",
    "bassline": "electronic",
    "uk funky": "electronic",
    "video game music": "electronic",
    "chiptune": "electronic",
    "bitpop": "electronic",
    "game boy music": "electronic",
    "shiny": "electronic",
    "skweee": "electronic",
    "nintendocore": "electronic",
    "splatune": "electronic",
    "stylophonic pop": "electronic",
    "alternative hip hop": "hip-hop/rap",
    "australian hip hop": "hip-hop/rap",
    "bongo flava": "hip-hop/rap",
    "boom bap": "hip-hop/rap",
    "british hip hop": "hip-hop/rap",
    "chap hop": "hip-hop/rap",
    "chopper": "hip-hop/rap",
    "christian hip hop": "hip-hop/rap",
    "cloud rap": "hip-hop/rap",
    "conscious hip hop": "hip-hop/rap",
    "crunk": "hip-hop/rap",
    "crunkcore": "hip-hop/rap",
    "drill": "hip-hop/rap",
    "experimental hip hop": "hip-hop/rap",
    "g-funk": "hip-hop/rap",
    "gangsta rap": "hip-hop/rap",
    "golden age hip hop": "hip-hop/rap",
    "grime": "hip-hop/rap",
    "hardcore hip hop": "hip-hop/rap",
    "hiplife": "hip-hop/rap",
    "hip pop": "hip-hop/rap",
    "hyphy": "hip-hop/rap",
    "industrial hip hop": "hip-hop/rap",
    "instrumental hip hop": "hip-hop/rap",
    "jazz rap": "jazz",
    "lyrical hip hop": "hip-hop/rap",
    "low bap": "hip-hop/rap",
    "merenrap": "hip-hop/rap",
    "motswako": "hip-hop/rap",
    "mumble rap": "hip-hop/rap",
    "nerdcore": "hip-hop/rap",
    "new jack swing": "r&b/soul",
    "new school hip hop": "hip-hop/rap",
    "old school hip hop": "hip-hop/rap",
    "political hip hop": "hip-hop/rap",
    "ragga": "hip-hop/rap",
    "reggaeton": "latin",
    "snap music": "hip-hop/rap",
    "jerkin'": "hip-hop/rap",
    "trap music": "hip-hop/rap",
    "urban pasifika": "hip-hop/rap",
    "west coast hip hop": "hip-hop/rap",
    "afro-cuban jazz": "latin",
    "alt-jazz": "jazz",
    "asian american jazz": "jazz",
    "avant-garde jazz": "jazz",
    "bebop": "jazz",
    "boogie-woogie": "jazz",
    "bossa nova": "latin",
    "british dance band": "jazz",
    "cape jazz": "jazz",
    "chamber jazz": "jazz",
    "continental jazz": "jazz",
    "cool jazz": "jazz",
    "crossover jazz": "jazz",
    "dixieland": "jazz",
    "ethno jazz": "jazz",
    "european free jazz": "jazz",
    "free funk": "jazz",
    "free improvisation": "jazz",
    "free jazz": "jazz",
    "gypsy jazz": "jazz",
    "hard bop": "jazz",
    "jazz blues": "jazz",
    "jazz-funk": "jazz",
    "jazz fusion": "jazz",
    "jazz rock": "rock",
    "kansas city jazz": "jazz",
    "latin jazz": "latin",
    "m-base": "jazz",
    "mainstream jazz": "jazz",
    "modal jazz": "jazz",
    "neo-bop jazz": "jazz",
    "neo-swing": "jazz",
    "novelty ragtime": "jazz",
    "orchestral jazz": "jazz",
    "post-bop": "jazz",
    "punk jazz": "jazz",
    "ragtime": "jazz",
    "shibuya-kei": "jazz",
    "ska jazz": "jazz",
    "smooth jazz": "jazz",
    "soul jazz": "jazz",
    "stride jazz": "jazz",
    "straight-ahead jazz": "jazz",
    "swing music": "jazz",
    "third stream": "jazz",
    "trad jazz": "jazz",
    "vocal jazz": "jazz",
    "west coast jazz": "jazz",
    "music of brazil": "latin",
    "ax\u00e9 music": "latin",
    "brazilian rock": "latin",
    "brega": "latin",
    "tecnobrega": "latin",
    "choro": "latin",
    "forr\u00f3": "latin",
    "frevo": "latin",
    "funk carioca": "latin",
    "lambada": "latin",
    "zouk-lambada": "latin",
    "maracatu": "latin",
    "m\u00fasica popular brasileira": "latin",
    "tropicalia": "latin",
    "m\u00fasica sertaneja": "country",
    "new mexico music": "country",
    "samba": "latin",
    "pagode": "latin",
    "samba rock": "latin",
    "latin christian music": "latin",
    "latin pop": "pop",
    "latin ballad": "pop",
    "latin swing": "latin",
    "latin rock": "latin",
    "latin alternative": "latin",
    "rock en espa\u00f1ol": "latin",
    "latin trap": "latin",
    "regional mexican": "latin",
    "banda": "latin",
    "norte\u00f1o": "latin",
    "traditional:": "latin",
    "flamenco": "latin",
    "tango music": "latin",
    "folk": "latin",
    "bullerengue": "latin",
    "fado": "pop",
    "grupera": "latin",
    "huayno": "latin",
    "mariachi": "country",
    "ranchera": "country",
    "mexican son music": "latin",
    "m\u00fasica criolla": "latin",
    "nueva canci\u00f3n": "latin",
    "tropical music": "latin",
    "bachata": "latin",
    "bolero": "latin",
    "criolla": "latin",
    "cumbia": "latin",
    "es:chicha": "latin",
    "porro": "latin",
    "guajira": "latin",
    "mambo": "latin",
    "merengue music": "latin",
    "cuban rumba": "latin",
    "salsa music": "latin",
    "salsa rom\u00e1ntica": "latin",
    "son": "latin",
    "tejano music": "country",
    "timba": "latin",
    "tropipop": "latin",
    "vallenato": "latin",
    "adult contemporary": "pop",
    "arabic pop music": "pop",
    "baroque pop": "pop",
    "brill building": "pop",
    "britpop": "pop",
    "bubblegum pop": "pop",
    "canci\u00f3n": "pop",
    "canzone": "pop",
    "chalga": "country",
    "chanson": "pop",
    "christian pop": "pop",
    "classical crossover": "pop",
    "country pop": "country",
    "c-pop": "pop",
    "hokkien pop": "pop",
    "mandopop": "pop",
    "europop": "pop",
    "austropop": "pop",
    "french pop music": "pop",
    "la\u00efk\u00f3": "pop",
    "nederpop": "pop",
    "russian pop": "pop",
    "folk pop": "pop",
    "iranian pop": "pop",
    "indie pop": "pop",
    "j-pop": "pop",
    "jangle pop": "pop",
    "k-pop": "pop",
    "korean hip hop": "pop",
    "korean rock": "pop",
    "t'ong guitar": "pop",
    "trot": "pop",
    "swamp pop": "pop",
    "mexican pop music": "pop",
    "new romantic": "pop",
    "operatic pop": "pop",
    "pop rap": "pop",
    "pop rock": "rock",
    "power pop": "pop",
    "soft rock": "rock",
    "pop punk": "rock",
    "neon pop": "rock",
    "emo pop": "rock",
    "pop soul": "pop",
    "progressive pop": "pop",
    "psychedelic pop": "pop",
    "rebetiko": "pop",
    "schlager music": "pop",
    "sophisti-pop": "pop",
    "space age pop": "pop",
    "sunshine pop": "pop",
    "surf music": "pop",
    "teen pop": "pop",
    "traditional pop music": "pop",
    "turkish pop music": "pop",
    "vispop": "pop",
    "wonky pop": "pop",
    "worldbeat": "rock",
    "funk": "r&b/soul",
    "deep funk": "r&b/soul",
    "go-go": "r&b/soul",
    "hip hop soul": "r&b/soul",
    "p-funk": "r&b/soul",
    "pbr&amp;b": "r&b/soul",
    "gospel music": "r&b/soul",
    "soul music": "r&b/soul",
    "blue-eyed soul": "r&b/soul",
    "northern soul": "r&b/soul",
    "neo soul": "r&b/soul",
    "southern soul": "r&b/soul",
    "alternative rock": "rock",
    "grunge": "rock",
    "post-grunge": "rock",
    "ocean grunge": "rock",
    "indie rock": "rock",
    "dunedin sound": "rock",
    "math rock": "rock",
    "post-punk revival": "rock",
    "sadcore": "rock",
    "dream pop": "rock",
    "shoegaze": "rock",
    "slowcore": "rock",
    "beat music": "rock",
    "christian rock": "rock",
    "dark cabaret": "rock",
    "experimental rock": "rock",
    "art rock": "rock",
    "post-punk": "rock",
    "gothic rock": "rock",
    "no wave": "rock",
    "noise rock": "rock",
    "post-rock": "rock",
    "post-metal": "rock",
    "folk rock": "country",
    "garage rock": "rock",
    "glam rock": "rock",
    "hard rock": "rock",
    "heavy metal music": "rock",
    "alternative metal": "rock",
    "funk metal": "rock",
    "nu metal": "rock",
    "rap metal": "rock",
    "avant-garde metal": "rock",
    "black metal": "rock",
    "symphonic black metal": "rock",
    "viking metal": "rock",
    "national socialist black metal": "rock",
    "atmospheric black metal": "rock",
    "melodic black metal": "rock",
    "ambient black metal": "rock",
    "depressive black metal": "rock",
    "depressive suicidal black metal": "rock",
    "war metal": "rock",
    "christian metal": "rock",
    "unblack metal": "rock",
    "death metal": "rock",
    "death 'n' roll": "rock",
    "melodic death metal": "rock",
    "technical death metal": "rock",
    "deathgrind": "rock",
    "doom metal": "rock",
    "death-doom": "rock",
    "drone metal": "rock",
    "folk metal": "rock",
    "celtic metal": "rock",
    "medieval metal": "rock",
    "pagan metal": "rock",
    "glam metal": "rock",
    "gothic metal": "rock",
    "kawaii metal": "rock",
    "latin metal": "rock",
    "metalcore": "rock",
    "melodic metalcore": "rock",
    "deathcore": "rock",
    "mathcore": "rock",
    "neoclassical metal": "rock",
    "power metal": "rock",
    "progressive metal": "rock",
    "djent": "rock",
    "sludge metal": "rock",
    "speed metal": "rock",
    "symphonic metal": "rock",
    "thrash metal": "rock",
    "crossover thrash": "rock",
    "groove metal": "rock",
    "new wave music": "rock",
    "world fusion": "rock",
    "paisley underground": "rock",
    "palm desert scene": "rock",
    "progressive rock": "rock",
    "canterbury scene": "rock",
    "new prog": "rock",
    "rock in opposition": "rock",
    "psychedelic rock": "rock",
    "acid rock": "rock",
    "freakbeat": "rock",
    "neo-psychedelia": "rock",
    "raga rock": "rock",
    "punk rock": "rock",
    "anarcho punk": "rock",
    "crust punk": "rock",
    "d-beat": "rock",
    "art punk": "rock",
    "christian punk": "rock",
    "deathrock": "rock",
    "folk punk": "rock",
    "celtic punk": "rock",
    "cowpunk": "country",
    "gypsy punk": "rock",
    "garage punk": "rock",
    "grindcore": "rock",
    "crustgrind": "rock",
    "noisegrind": "rock",
    "goregrind": "rock",
    "hardcore punk": "rock",
    "post-hardcore": "rock",
    "emo": "rock",
    "screamo": "rock",
    "thrashcore": "rock",
    "powerviolence": "rock",
    "street punk": "rock",
    "horror punk": "rock",
    "nazi punk": "rock",
    "psychobilly": "country",
    "riot grrrl": "rock",
    "ska punk": "rock",
    "skate punk": "rock",
    "rap rock": "rock",
    "rapcore": "rock",
    "eric lewis": "rock",
    "rock and roll": "rock",
    "southern rock": "rock",
    "stoner rock": "rock",
    "sufi rock": "rock",
    "surf rock": "rock",
    "visual kei": "rock",
    "nagoya kei": "rock",
    "alternative country": "country",
    "americana": "country",
    "australian country music": "country",
    "bakersfield sound": "country",
    "bluegrass music": "country",
    "progressive bluegrass": "country",
    "country rap": "country",
    "country rock": "country",
    "cajun music": "country",
    "cajun fiddle": "country",
    "christian country music": "country",
    "classic country": "country",
    "close harmony": "country",
    "dansband": "country",
    "honky-tonk": "country",
    "country music": "country",
    "nashville sound": "country",
    "neotraditional country": "country",
    "outlaw country": "country",
    "progressive country": "country",
    "red dirt": "country",
    "rockabilly": "country",
    "hellbilly music": "country",
    "texas country music": "country",
    "traditional country music": "country",
    "truck-driving country": "country",
    "western music": "country",
    "western swing": "country",
    "zydeco": "country",
    "american folk revival": "country",
    "anti-folk": "country",
    "british folk revival": "country",
    "celtic music": "country",
    "contemporary folk music": "country",
    "corrido": "country",
    "filk music": "country",
    "freak folk": "country",
    "indie folk": "country",
    "industrial folk music": "country",
    "neofolk": "country",
    "progressive folk music": "country",
    "protest song": "country",
    "psychedelic folk": "country",
    "singer-songwriter": "country",
    "skiffle": "country",
    "sung poetry": "country",
    "background music": "classical",
    "beautiful music": "classical",
    "muzak": "classical",
    "furniture music": "classical",
    "lounge music": "classical",
    "middle of the road": "classical"
}
